penaltyblog/__init__.py
penaltyblog/version.py
penaltyblog/backtest/__init__.py
penaltyblog/backtest/account.py
penaltyblog/backtest/backtest.py
penaltyblog/backtest/context.py
penaltyblog/bayes/__init__.py
penaltyblog/bayes/diagnostics.py
penaltyblog/bayes/likelihood.c
penaltyblog/bayes/likelihood.cp310-win_amd64.pyd
penaltyblog/bayes/sampler.c
penaltyblog/bayes/sampler.cp310-win_amd64.pyd
penaltyblog/bayes/sampler_api.py
penaltyblog/betting/__init__.py
penaltyblog/betting/arbitrage.py
penaltyblog/betting/kelly.py
penaltyblog/betting/odds.py
penaltyblog/betting/value_bets.py
penaltyblog/fpl/__init__.py
penaltyblog/fpl/fpl.py
penaltyblog/implied/__init__.py
penaltyblog/implied/implied.py
penaltyblog/implied/models.py
penaltyblog/matchflow/__init__.py
penaltyblog/matchflow/aggregates.py
penaltyblog/matchflow/aggs_registry.py
penaltyblog/matchflow/executor.py
penaltyblog/matchflow/flow.py
penaltyblog/matchflow/group.py
penaltyblog/matchflow/helpers.py
penaltyblog/matchflow/opta_helpers.py
penaltyblog/matchflow/opta_mappings.py
penaltyblog/matchflow/optimizer.py
penaltyblog/matchflow/plotting.py
penaltyblog/matchflow/predicates.py
penaltyblog/matchflow/predicates_helpers.py
penaltyblog/matchflow/query.py
penaltyblog/matchflow/contrib/__init__.py
penaltyblog/matchflow/contrib/opta.py
penaltyblog/matchflow/contrib/statsbomb.py
penaltyblog/matchflow/steps/__init__.py
penaltyblog/matchflow/steps/group.py
penaltyblog/matchflow/steps/source.py
penaltyblog/matchflow/steps/source_opta.py
penaltyblog/matchflow/steps/source_statsbomb.py
penaltyblog/matchflow/steps/transform.py
penaltyblog/matchflow/steps/utils.py
penaltyblog/matchflow/steps/opta/__init__.py
penaltyblog/matchflow/steps/opta/client.py
penaltyblog/matchflow/steps/opta/config.py
penaltyblog/matchflow/steps/opta/endpoints.py
penaltyblog/matchflow/steps/opta/exceptions.py
penaltyblog/matchflow/steps/opta/paginator.py
penaltyblog/matchflow/steps/opta/parsers.py
penaltyblog/metrics/__init__.py
penaltyblog-1.8.0.dist-info/licenses/LICENCE
penaltyblog-1.8.0.dist-info/METADATA
penaltyblog-1.8.0.dist-info/WHEEL
penaltyblog-1.8.0.dist-info/top_level.txt
penaltyblog-1.8.0.dist-info/RECORD
