Metadata-Version: 2.4
Name: penaltyblog
Version: 1.8.0
Summary: Football (soccer) Data & Modelling Made Easy
Author-email: Martin Eastwood <martin.eastwood@gmx.com>
Project-URL: Homepage, https://github.com/martineastwood/penaltyblog
Project-URL: Repository, https://github.com/martineastwood/penaltyblog
Keywords: football,soccer,goals,modelling,dixon coles,poisson,scraper,scraping,backtest,matchflow
Classifier: Programming Language :: Python :: 3
Classifier: Programming Language :: Python :: 3.10
Classifier: Programming Language :: Python :: 3.11
Classifier: Programming Language :: Python :: 3.12
Classifier: Programming Language :: Python :: 3.13
Requires-Python: >=3.10
License-File: LICENCE
Requires-Dist: beautifulsoup4
Requires-Dist: cssselect
Requires-Dist: cython
Requires-Dist: fsspec
Requires-Dist: html5lib
Requires-Dist: ipywidgets
Requires-Dist: kaleido
Requires-Dist: lxml
Requires-Dist: matplotlib
Requires-Dist: networkx
Requires-Dist: numpy
Requires-Dist: orjson
Requires-Dist: pandas
Requires-Dist: plotly
Requires-Dist: pulp
Requires-Dist: requests
Requires-Dist: scipy
Requires-Dist: socks
Requires-Dist: statsbombpy
Requires-Dist: tabulate
Requires-Dist: tqdm
Requires-Dist: wrapper-tls-requests
Provides-Extra: dev
Requires-Dist: black>=22.6.0; extra == "dev"
Requires-Dist: build; extra == "dev"
Requires-Dist: coveralls>=3.3.1; extra == "dev"
Requires-Dist: coverage>=6.4.2; extra == "dev"
Requires-Dist: ipython>=8.4.0; extra == "dev"
Requires-Dist: jupyterlab>=3.4.4; extra == "dev"
Requires-Dist: jupyterlab-code-formatter>=1.5.2; extra == "dev"
Requires-Dist: nbsphinx>=0.8.9; extra == "dev"
Requires-Dist: numpydoc>=1.4.0; extra == "dev"
Requires-Dist: pre-commit>=2.20.0; extra == "dev"
Requires-Dist: Pygments>=2.12.0; extra == "dev"
Requires-Dist: pytest>=7.1.2; extra == "dev"
Requires-Dist: pytest-vcr; extra == "dev"
Requires-Dist: setuptools>=75.6.0; extra == "dev"
Requires-Dist: Sphinx>=5.1.1; extra == "dev"
Requires-Dist: sphinx-rtd-theme>=1.0.0; extra == "dev"
Requires-Dist: types-requests>=2.28.11; extra == "dev"
Requires-Dist: vcrpy; extra == "dev"
Provides-Extra: s3
Requires-Dist: s3fs; extra == "s3"
Provides-Extra: gcs
Requires-Dist: gcsfs; extra == "gcs"
Requires-Dist: gcloud; extra == "gcs"
Provides-Extra: azure
Requires-Dist: adlfs; extra == "azure"
Provides-Extra: cloud
Requires-Dist: s3fs; extra == "cloud"
Requires-Dist: gcsfs; extra == "cloud"
Requires-Dist: adlfs; extra == "cloud"
Requires-Dist: gcloud; extra == "cloud"
Dynamic: license-file
